techrec/__init__.py
techrec/cli.py
techrec/config_manager.py
techrec/db.py
techrec/forge.py
techrec/http_retriever.py
techrec/maint.py
techrec/server.py
techrec/test_forge.py
techrec/pages/archive.html
techrec/pages/new.html
techrec/pages/old.html
techrec/static/css/font-awesome.css
techrec/static/css/jquery-ui.min.css
techrec/static/css/pure-min.css
techrec/static/css/pure-skin-porpora.css
techrec/static/css/style.css
techrec/static/css/techrec.css
techrec/static/fonts/FontAwesome.otf
techrec/static/fonts/fontawesome-webfont.eot
techrec/static/fonts/fontawesome-webfont.svg
techrec/static/fonts/fontawesome-webfont.ttf
techrec/static/fonts/fontawesome-webfont.woff
techrec/static/img/7915.orig.png
techrec/static/img/7915.png
techrec/static/img/ajax-loader.gif
techrec/static/img/button.jpg
techrec/static/img/icon.ico
techrec/static/js/archive.js
techrec/static/js/jquery-1.9.1.min.js
techrec/static/js/jquery-ui.min.js
techrec/static/js/jquery.form.min.js
techrec/static/js/jquery.ui.datepicker-it.min.js
techrec/static/js/new.js
techrec/static/js/old.js
techrec/static/js/rec.js
techrec/static/js/ui.js
techrec/static/js/underscore-min.js
techrec/static/techrec/jquery-1.9.1.min.js
techrec-2.1.0.dist-info/licenses/LICENSE
techrec-2.1.0.dist-info/METADATA
techrec-2.1.0.dist-info/WHEEL
techrec-2.1.0.dist-info/entry_points.txt
techrec-2.1.0.dist-info/top_level.txt
techrec-2.1.0.dist-info/RECORD
