Metadata-Version: 2.4
Name: techrec
Version: 2.1.0
Summary: A radio automation based on MPD
Author-email: boyska <piuttosto@logorroici.org>
License: AGPL-3.0-only
Project-URL: Homepage, https://git.lattuga.net/techbloc/techrec
Project-URL: Repository, https://git.lattuga.net/techbloc/techrec
Project-URL: Issues, https://git.lattuga.net/techbloc/techrec/issues
Keywords: music
Classifier: License :: OSI Approved :: GNU Affero General Public License v3
Classifier: Topic :: Multimedia :: Sound/Audio
Requires-Python: >=3.9
License-File: LICENSE
Requires-Dist: aiofiles==24.1.*
Requires-Dist: aiohttp==3.11.*
Requires-Dist: anyio==3.6.2
Requires-Dist: async-timeout==4.*
Requires-Dist: attrs==22.2.0
Requires-Dist: chardet==3.0.4
Requires-Dist: click==7.1.2
Requires-Dist: fastapi==0.115.*
Requires-Dist: h11==0.11.0
Requires-Dist: pydantic==2.10.*
Requires-Dist: SQLAlchemy==1.4.25
Requires-Dist: toml==0.10.*; python_version < "3.11"
Requires-Dist: uvicorn==0.34.0
Provides-Extra: dev
Requires-Dist: pytest; extra == "dev"
Requires-Dist: pytest-asyncio; extra == "dev"
Requires-Dist: types-setuptools; extra == "dev"
Requires-Dist: sqlalchemy-stubs; extra == "dev"
Requires-Dist: types-aiofiles==24.1.*; extra == "dev"
Dynamic: license-file
